MANIFEST.in
setup.cfg
setup.py
django_mbase.egg-info/PKG-INFO
django_mbase.egg-info/SOURCES.txt
django_mbase.egg-info/dependency_links.txt
django_mbase.egg-info/not-zip-safe
django_mbase.egg-info/top_level.txt
mbase/__init__.py
mbase/admin.py
mbase/apps.py
mbase/conf.py
mbase/models.py
mbase/tests.py
mbase/views.py
mbase/migrations/__init__.py
mbase/templatetags/__init__.py
mbase/templatetags/mbase.py