Metadata-Version: 1.1
Name: django-mbase
Version: 0.2
Summary: Basic abstracts models and usefull stuff for Django
Home-page: https://github.com/synw/django-mbase
Author: synw
Author-email: synwe@yahoo.com
License: UNKNOWN
Download-URL: https://github.com/synw/django-mbase/releases/tag/0.2
Keywords: django
Platform: UNKNOWN
Classifier: Development Status :: 3 - Alpha
Classifier: Framework :: Django :: 1.9
Classifier: Intended Audience :: Developers
Classifier: License :: OSI Approved :: MIT License
Classifier: Programming Language :: Python :: 2.7
